neoversity_group1_assistant_bot-1.0.2.dist-info/licenses/LICENSE
src/__init__.py
src/application/__init__.py
src/application/commands/__init__.py
src/application/commands/contact_commands.py
src/application/commands/note_commands.py
src/application/exceptions/__init__.py
src/application/exceptions/base.py
src/application/services/__init__.py
src/application/services/contact_service.py
src/application/services/note_service.py
src/config/__init__.py
src/config/command_args_config.py
src/config/confidence_config.py
src/config/date_format_config.py
src/config/entity_config.py
src/config/intent_config.py
src/config/intent_requirements.py
src/config/keyword_map.py
src/config/model_config.py
src/config/nlp_config.py
src/config/phone_config.py
src/config/pipeline_definitions.py
src/config/regex_patterns.py
src/config/storage_config.py
src/config/ui_config.py
src/config/validation_config.py
src/domain/__init__.py
src/domain/address_book.py
src/domain/notebook.py
src/domain/entities/__init__.py
src/domain/entities/contact.py
src/domain/entities/entity.py
src/domain/entities/note.py
src/domain/mappers/__init__.py
src/domain/mappers/contact_mapper.py
src/domain/mappers/note_mapper.py
src/domain/models/__init__.py
src/domain/models/dbbase.py
src/domain/models/dbcontact.py
src/domain/models/dbnote.py
src/domain/utils/__init__.py
src/domain/utils/birthday_utils.py
src/domain/utils/id_generator.py
src/domain/utils/styles_utils.py
src/domain/validators/__init__.py
src/domain/validators/address_validator.py
src/domain/validators/base_validator.py
src/domain/validators/birthday_validator.py
src/domain/validators/email_validator.py
src/domain/validators/intent_validator.py
src/domain/validators/name_validator.py
src/domain/validators/note_text_validator.py
src/domain/validators/phone_validator.py
src/domain/validators/tag_validator.py
src/domain/value_objects/__init__.py
src/domain/value_objects/address.py
src/domain/value_objects/birthday.py
src/domain/value_objects/email.py
src/domain/value_objects/field.py
src/domain/value_objects/name.py
neoversity_group1_assistant_bot-1.0.2.dist-info/METADATA
neoversity_group1_assistant_bot-1.0.2.dist-info/WHEEL
neoversity_group1_assistant_bot-1.0.2.dist-info/top_level.txt
neoversity_group1_assistant_bot-1.0.2.dist-info/RECORD
