Metadata-Version: 2.4
Name: neoversity-group1-assistant-bot
Version: 1.0.2
Summary: Students project for learning Python
Home-page: https://github.com/kms-engineer/assistant-bot.git
Author: Neoversity Group1 Team
Author-email: Oleksandr Popov <oleksandr.popov@outlook.com>
License-Expression: Apache-2.0
Project-URL: Homepage, https://github.com/kms-engineer/assistant-bot
Project-URL: Issues, https://github.com/kms-engineer/assistant-bot/issues
Classifier: Programming Language :: Python :: 3
Classifier: Operating System :: OS Independent
Requires-Python: >=3.10
License-File: LICENSE
Requires-Dist: sqlalchemy==2.0.44
Requires-Dist: phonenumbers>=8.12.0
Requires-Dist: email-validator>=1.1.0
Requires-Dist: python-dateutil>=2.8.0
Requires-Dist: colorama==0.4.6
Requires-Dist: transformers>=4.30.0
Requires-Dist: torch>=2.0.0
Requires-Dist: sentencepiece>=0.1.99
Requires-Dist: scikit-learn>=1.0.0
Requires-Dist: huggingface_hub>=0.16.0
Requires-Dist: fastmcp==2.13.0
Dynamic: license-file
